{"cameraMode":{"drawMode":0,"name":"Shaded","section":"Shading Mode"},"sceneLighting":true,"audioPlay":false,"sceneViewState":{"m_AlwaysRefresh":false,"showFog":true,"showSkybox":true,"showFlares":true,"showImageEffects":true,"showParticleSystems":true,"showVisualEffectGraphs":true,"m_FxEnabled":true},"in2DMode":false,"pivot":{"x":424.078857421875,"y":-65.24191284179688,"z":54.38518142700195},"rotation":{"x":-0.27688464522361758,"y":-0.7032424807548523,"z":0.35311299562454226,"w":-0.5515543222427368},"size":170.2692108154297,"orthographic":false}